mathyd.py
mathyd-0.1.4.dist-info/LICENSE.txt
mathyd-0.1.4.dist-info/METADATA
mathyd-0.1.4.dist-info/WHEEL
mathyd-0.1.4.dist-info/top_level.txt
mathyd-0.1.4.dist-info/RECORD
