Metadata-Version: 2.1
Name: mathyd
Version: 0.1.4
Summary: ...
Home-page: https://code.xueersi.com/ide/code/44284495
Author: ruyiding
Author-email: ruyiding_20120424@163.com
License: MIT
Classifier: License :: OSI Approved :: MIT License
Classifier: Programming Language :: Python
Classifier: Programming Language :: Python :: 3
Classifier: Programming Language :: Python :: 3.6
Classifier: Programming Language :: Python :: Implementation :: CPython
Classifier: Programming Language :: Python :: Implementation :: PyPy
Requires-Python: >=3.1.0
License-File: LICENSE.txt
